{
  "pipeline_version": "1.0.0",
  "config_version": "1.0.0",
  "normality_tests": [],
  "omnibus_tests": [
    {
      "model": "Sonnet 4.5",
      "metric": "pass_rate",
      "n_groups": 7,
      "h_statistic": NaN,
      "p_value": NaN,
      "is_significant": false
    },
    {
      "model": "Sonnet 4.5",
      "metric": "impl_rate",
      "n_groups": 7,
      "h_statistic": NaN,
      "p_value": NaN,
      "is_significant": false
    }
  ],
  "pairwise_comparisons": [
    {
      "model": "Sonnet 4.5",
      "tier1": "T0",
      "tier2": "T1",
      "n1": 1,
      "n2": 1,
      "u_statistic": 0.0,
      "metric": "pass_rate",
      "p_value_raw": 1.0,
      "p_value": 1.0,
      "is_significant": false
    },
    {
      "model": "Sonnet 4.5",
      "tier1": "T1",
      "tier2": "T2",
      "n1": 1,
      "n2": 1,
      "u_statistic": 0.0,
      "metric": "pass_rate",
      "p_value_raw": 1.0,
      "p_value": 1.0,
      "is_significant": false
    },
    {
      "model": "Sonnet 4.5",
      "tier1": "T2",
      "tier2": "T3",
      "n1": 1,
      "n2": 1,
      "u_statistic": 0.0,
      "metric": "pass_rate",
      "p_value_raw": 1.0,
      "p_value": 1.0,
      "is_significant": false
    },
    {
      "model": "Sonnet 4.5",
      "tier1": "T3",
      "tier2": "T4",
      "n1": 1,
      "n2": 1,
      "u_statistic": 0.0,
      "metric": "pass_rate",
      "p_value_raw": 1.0,
      "p_value": 1.0,
      "is_significant": false
    },
    {
      "model": "Sonnet 4.5",
      "tier1": "T4",
      "tier2": "T5",
      "n1": 1,
      "n2": 1,
      "u_statistic": 0.0,
      "metric": "pass_rate",
      "p_value_raw": 1.0,
      "p_value": 1.0,
      "is_significant": false
    },
    {
      "model": "Sonnet 4.5",
      "tier1": "T5",
      "tier2": "T6",
      "n1": 1,
      "n2": 1,
      "u_statistic": 0.0,
      "metric": "pass_rate",
      "p_value_raw": 1.0,
      "p_value": 1.0,
      "is_significant": false
    }
  ],
  "effect_sizes": [],
  "correlations": [
    {
      "model": "Sonnet 4.5",
      "metric1": "score",
      "metric2": "cost_usd",
      "n": 7,
      "spearman_rho": -0.630061919161936,
      "p_value": 0.1293597076444284,
      "is_significant": false
    },
    {
      "model": "Sonnet 4.5",
      "metric1": "score",
      "metric2": "total_tokens",
      "n": 7,
      "spearman_rho": -0.4076871241636057,
      "p_value": 0.36394248359194625,
      "is_significant": false
    },
    {
      "model": "Sonnet 4.5",
      "metric1": "score",
      "metric2": "duration_seconds",
      "n": 7,
      "spearman_rho": 0.03706246583305506,
      "p_value": 0.9371240086628561,
      "is_significant": false
    },
    {
      "model": "Sonnet 4.5",
      "metric1": "score",
      "metric2": "impl_rate",
      "n": 7,
      "spearman_rho": 0.9349469900084572,
      "p_value": 0.0020013213852761807,
      "is_significant": true
    },
    {
      "model": "Sonnet 4.5",
      "metric1": "impl_rate",
      "metric2": "cost_usd",
      "n": 7,
      "spearman_rho": -0.5765999761251578,
      "p_value": 0.17538182452245643,
      "is_significant": false
    },
    {
      "model": "Sonnet 4.5",
      "metric1": "impl_rate",
      "metric2": "duration_seconds",
      "n": 7,
      "spearman_rho": -0.03603749850782236,
      "p_value": 0.9388605613942139,
      "is_significant": false
    },
    {
      "model": "Sonnet 4.5",
      "metric1": "cost_usd",
      "metric2": "total_tokens",
      "n": 7,
      "spearman_rho": 0.8928571428571429,
      "p_value": 0.006807187408935393,
      "is_significant": true
    }
  ],
  "tier_descriptives": [
    {
      "model": "Sonnet 4.5",
      "tier": "T0",
      "n": 1,
      "pass_rate": 1.0,
      "mean_cost": 0.1351093,
      "median_cost": 0.1351093,
      "cop": 0.1351093
    },
    {
      "model": "Sonnet 4.5",
      "tier": "T1",
      "n": 1,
      "pass_rate": 1.0,
      "mean_cost": 0.1273926,
      "median_cost": 0.1273926,
      "cop": 0.1273926
    },
    {
      "model": "Sonnet 4.5",
      "tier": "T2",
      "n": 1,
      "pass_rate": 1.0,
      "mean_cost": 0.1379989,
      "median_cost": 0.1379989,
      "cop": 0.1379989
    },
    {
      "model": "Sonnet 4.5",
      "tier": "T3",
      "n": 1,
      "pass_rate": 1.0,
      "mean_cost": 0.1294133,
      "median_cost": 0.1294133,
      "cop": 0.1294133
    },
    {
      "model": "Sonnet 4.5",
      "tier": "T4",
      "n": 1,
      "pass_rate": 1.0,
      "mean_cost": 0.1684904,
      "median_cost": 0.1684904,
      "cop": 0.1684904
    },
    {
      "model": "Sonnet 4.5",
      "tier": "T5",
      "n": 1,
      "pass_rate": 1.0,
      "mean_cost": 0.06531415,
      "median_cost": 0.06531415,
      "cop": 0.06531415
    },
    {
      "model": "Sonnet 4.5",
      "tier": "T6",
      "n": 1,
      "pass_rate": 1.0,
      "mean_cost": 0.24744315,
      "median_cost": 0.24744315,
      "cop": 0.24744315
    },
    {
      "model": "Sonnet 4.5",
      "tier": "frontier",
      "n": 7,
      "pass_rate": null,
      "mean_cost": null,
      "median_cost": null,
      "cop": 0.06531415,
      "frontier_tier": "T5"
    }
  ]
}
